audio_separator/__init__.py
audio_separator/models.json
audio_separator/separator/__init__.py
audio_separator/separator/architectures/__init__.py
audio_separator/separator/architectures/demucs_separator.py
audio_separator/separator/architectures/mdx_separator.py
audio_separator/separator/architectures/mdxc_separator.py
audio_separator/separator/architectures/vr_separator.py
audio_separator/separator/common_separator.py
audio_separator/separator/separator.py
audio_separator/separator/uvr_lib_v5/__init__.py
audio_separator/separator/uvr_lib_v5/demucs/__init__.py
audio_separator/separator/uvr_lib_v5/demucs/__main__.py
audio_separator/separator/uvr_lib_v5/demucs/apply.py
audio_separator/separator/uvr_lib_v5/demucs/demucs.py
audio_separator/separator/uvr_lib_v5/demucs/filtering.py
audio_separator/separator/uvr_lib_v5/demucs/hdemucs.py
audio_separator/separator/uvr_lib_v5/demucs/htdemucs.py
audio_separator/separator/uvr_lib_v5/demucs/model.py
audio_separator/separator/uvr_lib_v5/demucs/model_v2.py
audio_separator/separator/uvr_lib_v5/demucs/pretrained.py
audio_separator/separator/uvr_lib_v5/demucs/repo.py
audio_separator/separator/uvr_lib_v5/demucs/spec.py
audio_separator/separator/uvr_lib_v5/demucs/states.py
audio_separator/separator/uvr_lib_v5/demucs/tasnet.py
audio_separator/separator/uvr_lib_v5/demucs/tasnet_v2.py
audio_separator/separator/uvr_lib_v5/demucs/transformer.py
audio_separator/separator/uvr_lib_v5/demucs/utils.py
audio_separator/separator/uvr_lib_v5/mdxnet.py
audio_separator/separator/uvr_lib_v5/mixer.ckpt
audio_separator/separator/uvr_lib_v5/modules.py
audio_separator/separator/uvr_lib_v5/playsound.py
audio_separator/separator/uvr_lib_v5/pyrb.py
audio_separator/separator/uvr_lib_v5/results.py
audio_separator/separator/uvr_lib_v5/roformer/attend.py
audio_separator/separator/uvr_lib_v5/roformer/bs_roformer.py
audio_separator/separator/uvr_lib_v5/roformer/mel_band_roformer.py
audio_separator/separator/uvr_lib_v5/spec_utils.py
audio_separator_ui-0.25.0.dist-info/LICENSE
audio_separator_ui-0.25.0.dist-info/METADATA
audio_separator_ui-0.25.0.dist-info/WHEEL
audio_separator_ui-0.25.0.dist-info/entry_points.txt
audio_separator_ui-0.25.0.dist-info/RECORD
