Metadata-Version: 2.1
Name: audio-separator-ui
Version: 0.25.0
Summary: Easy to use audio stem separation with a UI, using various models from UVR trained primarily by @Anjok07
Home-page: https://github.com/Bebra777228/Audio-Separator-UI
License: MIT
Keywords: audio,sound,karaoke,ui
Author: Andrew Beveridge
Author-email: andrew@beveridge.uk
Requires-Python: >=3.10
Classifier: Development Status :: 4 - Beta
Classifier: Intended Audience :: Developers
Classifier: Intended Audience :: Science/Research
Classifier: License :: OSI Approved :: MIT License
Classifier: Operating System :: OS Independent
Classifier: Programming Language :: Python :: 3
Classifier: Programming Language :: Python :: 3.10
Classifier: Programming Language :: Python :: 3.11
Classifier: Programming Language :: Python :: 3.12
Classifier: Programming Language :: Python :: 3.13
Classifier: Topic :: Multimedia :: Sound/Audio
Classifier: Topic :: Multimedia :: Sound/Audio :: Mixers
Provides-Extra: cpu
Provides-Extra: gpu
Requires-Dist: beartype (>=0.18.5,<0.19.0)
Requires-Dist: diffq (>=0.2) ; sys_platform != "win32"
Requires-Dist: diffq-fixed (>=0.2) ; sys_platform == "win32"
Requires-Dist: einops (>=0.7)
Requires-Dist: gradio
Requires-Dist: julius (>=0.2)
Requires-Dist: librosa (>=0.10)
Requires-Dist: ml_collections
Requires-Dist: numpy (>=1.23,<2)
Requires-Dist: onnx (>=1.14)
Requires-Dist: onnx2torch (>=1.5)
Requires-Dist: onnxruntime (>=1.17) ; extra == "cpu"
Requires-Dist: onnxruntime-gpu (>=1.17) ; extra == "gpu"
Requires-Dist: pydub (>=0.25)
Requires-Dist: pyyaml
Requires-Dist: requests (>=2)
Requires-Dist: resampy (>=0.4)
Requires-Dist: rotary-embedding-torch (>=0.6.1,<0.7.0)
Requires-Dist: samplerate (==0.1.0)
Requires-Dist: scipy (>=1.13.0,<2.0.0)
Requires-Dist: six (>=1.16)
Requires-Dist: torch (>=2.3,<2.5)
Requires-Dist: tqdm
Project-URL: Documentation, https://github.com/Bebra777228/Audio-Separator-UI/blob/main/README.md
Project-URL: Repository, https://github.com/Bebra777228/Audio-Separator-UI
